MANIFEST.in
README.rst
setup.py
bin/funniest-joke
funniest_dnt17/__init__.py
funniest_dnt17/command_line.py
funniest_dnt17.egg-info/PKG-INFO
funniest_dnt17.egg-info/SOURCES.txt
funniest_dnt17.egg-info/dependency_links.txt
funniest_dnt17.egg-info/entry_points.txt
funniest_dnt17.egg-info/requires.txt
funniest_dnt17.egg-info/top_level.txt