Metadata-Version: 1.1
Name: funniest-dnt17
Version: 0.6
Summary: The funniest joke in the world
Home-page: https://github.com/dnt17/funniest_dnt17
Author: Devin Turner
Author-email: devinturner17@gmail.com
License: MIT
Keywords: funniest joke comedy flying circus tutorial
Platform: UNKNOWN
Classifier: Development Status :: 3 - Alpha
Classifier: License :: OSI Approved :: MIT License
Classifier: Programming Language :: Python :: 2.7
Classifier: Topic :: Text Processing :: Linguistic
